Metadata-Version: 2.1
Name: py2captcha
Version: 0.1.1
Summary: Client library for solve captchas with 2captcha.com support.
Home-page: https://github.com/sdasolutions/py2captcha
Author: SDASolutions
Author-email: sdasolutions.co@gmail.com
License: MIT
Keywords: CAPTCHA,reCAPTCHA
Platform: UNKNOWN
Classifier: Intended Audience :: Developers
Classifier: Operating System :: OS Independent
Classifier: Topic :: Internet
Classifier: Programming Language :: Python
Classifier: License :: OSI Approved :: MIT License
